faceunlock/__init__.py
faceunlock/face_recognition.py
faceunlock/face_training.py
faceunlock/facedatacollect.py
faceunlock/facedetection.py
faceunlock-0.0.1.dist-info/LICENSE
faceunlock-0.0.1.dist-info/METADATA
faceunlock-0.0.1.dist-info/WHEEL
faceunlock-0.0.1.dist-info/top_level.txt
faceunlock-0.0.1.dist-info/RECORD
