Metadata-Version: 2.1
Name: faceunlock
Version: 0.0.1
Summary: ranking metrics
Home-page: https://pypi.org/happy_is_i
Author: Ray&Happy
Author-email: wdnmd@114514.com
License: MIT
Keywords: pypi,Ray,Happy,opencv
Platform: UNKNOWN
Classifier: Programming Language :: Python :: 3
Classifier: License :: OSI Approved :: MIT License
License-File: LICENSE
Requires-Dist: numpy
Requires-Dist: opencv-python
Requires-Dist: opencv-contrib-python
Requires-Dist: pillow
